{
    "fields": [
        "name",
        "operator",
        "surface",
        "width",
        "maxspeed",
        "oneway",
        "lanes",
        "nps/trailuse",
        "structure"
    ],
    "geometry": [
        "line"
    ],
    "icon": "highway-secondary",
    "matchScore": 1,
    "name": "Secondary Road",
    "searchable": true,
    "tags": {
        "highway": "secondary"
    },
    "terms": [
        "secondary road",
        "secondary",
        "road",
        "us highway",
        "state highway",
        "county highway"
    ]
}